discover_overlay/__init__.py
discover_overlay/__main__.py
discover_overlay/audio_assist.py
discover_overlay/autostart.py
discover_overlay/discord_connector.py
discover_overlay/discover_overlay.py
discover_overlay/draggable_window.py
discover_overlay/draggable_window_wayland.py
discover_overlay/image_getter.py
discover_overlay/notification_overlay.py
discover_overlay/overlay.py
discover_overlay/settings_window.py
discover_overlay/text_overlay.py
discover_overlay/voice_overlay.py
discover_overlay/glade/settings.glade
discover_overlay/locales/cy/LC_MESSAGES/default.mo
discover_overlay/locales/de/LC_MESSAGES/default.mo
discover_overlay/locales/en/LC_MESSAGES/default.mo
discover_overlay/locales/fr/LC_MESSAGES/default.mo
discover_overlay/locales/tr/LC_MESSAGES/default.mo
discover_overlay-0.7.9.data/data/share/applications/discover_overlay.desktop
discover_overlay-0.7.9.data/data/share/applications/discover_overlay_configure.desktop
discover_overlay-0.7.9.data/data/share/icons/hicolor/256x256/apps/discover-overlay-default.png
discover_overlay-0.7.9.data/data/share/icons/hicolor/256x256/apps/discover-overlay-tray.png
discover_overlay-0.7.9.data/data/share/icons/hicolor/256x256/apps/discover-overlay.png
discover_overlay-0.7.9.data/data/share/icons/hicolor/scalable/apps/discover-overlay-default.svg
discover_overlay-0.7.9.data/data/share/icons/hicolor/scalable/apps/discover-overlay-tray.svg
discover_overlay-0.7.9.data/data/share/icons/hicolor/scalable/apps/discover-overlay.svg
discover_overlay-0.7.9.dist-info/licenses/LICENSE
discover_overlay-0.7.9.dist-info/METADATA
discover_overlay-0.7.9.dist-info/WHEEL
discover_overlay-0.7.9.dist-info/entry_points.txt
discover_overlay-0.7.9.dist-info/top_level.txt
discover_overlay-0.7.9.dist-info/RECORD
