Metadata-Version: 2.4
Name: discover-overlay
Version: 0.7.9
Summary: Voice chat overlay
Home-page: https://github.com/trigg/Discover
Author: trigg
Author-email: 
License: GPLv3+
Keywords: discord overlay voice linux
Classifier: Development Status :: 4 - Beta
Classifier: Environment :: X11 Applications :: GTK
Classifier: Intended Audience :: End Users/Desktop
Classifier: License :: OSI Approved :: GNU General Public License v3 or later (GPLv3+)
Classifier: Operating System :: POSIX :: Linux
Classifier: Programming Language :: Python :: 3 :: Only
Classifier: Topic :: Communications :: Chat
Classifier: Topic :: Communications :: Conferencing
License-File: LICENSE
Requires-Dist: PyGObject>=3.22
Requires-Dist: websocket-client
Requires-Dist: pyxdg
Requires-Dist: requests
Requires-Dist: pillow
Requires-Dist: python-xlib
Requires-Dist: setuptools
Requires-Dist: pulsectl-asyncio
Dynamic: author
Dynamic: classifier
Dynamic: description
Dynamic: description-content-type
Dynamic: home-page
Dynamic: keywords
Dynamic: license
Dynamic: license-file
Dynamic: requires-dist
Dynamic: summary
